AI/__init__.py
AI/loss.py
AI/metrics.py
AI/train.py
AI/utils.py
TENSORFLOW/__init__.py
TORCH/__init__.py
ecg/__init__.py
ecg/peak_finder.py
ecg/physionet.py
ecg/plotter.py
ecg/processor.py
ecg/AF/Pwave.py
ecg/AF/RR.py
ecg/AF/__init__.py
nubilus-0.0.0.1a1.dist-info/METADATA
nubilus-0.0.0.1a1.dist-info/WHEEL
nubilus-0.0.0.1a1.dist-info/top_level.txt
nubilus-0.0.0.1a1.dist-info/RECORD
