Metadata-Version: 2.4
Name: nubilus
Version: 0.0.0.1a1
Summary: A UX-friendly AI learning framework with signal processing and multi-process support
Author: shyubi
Author-email: sjslife97@gmail.com
License: MIT
Keywords: AI,deep learning,UX,signal processing,nubilus
Classifier: Programming Language :: Python :: 3
Classifier: Operating System :: OS Independent
Classifier: Intended Audience :: Developers
Classifier: License :: OSI Approved :: MIT License
Requires-Python: >=3.10
Requires-Dist: numpy
Requires-Dist: numba
Requires-Dist: scipy
Requires-Dist: wfdb
Requires-Dist: matplotlib
Requires-Dist: scikit-learn
Requires-Dist: PyWavelets
Dynamic: author
Dynamic: author-email
Dynamic: classifier
Dynamic: description
Dynamic: description-content-type
Dynamic: keywords
Dynamic: license
Dynamic: requires-dist
Dynamic: requires-python
Dynamic: summary
